getversions/__init__.py
getversions/__main__.py
getversions/getversions.py
getversions/main.py
getversions/py.typed
getversions-0.1.0.dist-info/LICENSE
getversions-0.1.0.dist-info/METADATA
getversions-0.1.0.dist-info/WHEEL
getversions-0.1.0.dist-info/entry_points.txt
getversions-0.1.0.dist-info/top_level.txt
getversions-0.1.0.dist-info/RECORD
